awscli_plugin_endpoint/__init__.py
awscli_plugin_endpoint-0.4.dist-info/LICENSE
awscli_plugin_endpoint-0.4.dist-info/METADATA
awscli_plugin_endpoint-0.4.dist-info/WHEEL
awscli_plugin_endpoint-0.4.dist-info/top_level.txt
awscli_plugin_endpoint-0.4.dist-info/RECORD
