Metadata-Version: 2.1
Name: awscli-plugin-endpoint
Version: 0.4
Summary: Endpoint plugin for AWS CLI
Home-page: https://github.com/wbingli/awscli-plugin-endpoint
Author: Wenbing Li
Author-email: wbingli@gmail.com
License: UNKNOWN
Download-URL: https://github.com/wbingli/awscli-plugin-endpoint/tarball/0.4
Keywords: awscli,plugin,endpoint
Platform: UNKNOWN
Requires-Dist: awscli (>=1.11.0)
